tidylinreg/__init__.py
tidylinreg/tidylinreg.py
tidylinreg-1.1.5.dist-info/LICENSE
tidylinreg-1.1.5.dist-info/METADATA
tidylinreg-1.1.5.dist-info/WHEEL
tidylinreg-1.1.5.dist-info/RECORD
