Metadata-Version: 2.3
Name: tidylinreg
Version: 1.1.5
Summary: A linear regression package with statistical testing for each estimator.
License: MIT
Author: Benjamin Frizzell, Danish Karlin Isa, Nicholas Varabioff, Yasmin Hassan
Requires-Python: >=3.13
Classifier: License :: OSI Approved :: MIT License
Classifier: Programming Language :: Python :: 3
Classifier: Programming Language :: Python :: 3.13
Requires-Dist: matplotlib (>=3.10.0,<4.0.0)
Requires-Dist: numpy (>=2.2.1,<3.0.0)
Requires-Dist: pandas (>=2.2.3,<3.0.0)
Requires-Dist: scikit-learn (>=1.6.1,<2.0.0)
Requires-Dist: scipy (>=1.15.1,<2.0.0)
